COPYING.txt
HACKING.rst
MANIFEST.in
NEWS.rst
README.rst
conf.py
setup.cfg
setup.py
tox.ini
lazr/__init__.py
lazr.smtptest.egg-info/PKG-INFO
lazr.smtptest.egg-info/SOURCES.txt
lazr.smtptest.egg-info/dependency_links.txt
lazr.smtptest.egg-info/namespace_packages.txt
lazr.smtptest.egg-info/not-zip-safe
lazr.smtptest.egg-info/requires.txt
lazr.smtptest.egg-info/top_level.txt
lazr/smtptest/__init__.py
lazr/smtptest/controller.py
lazr/smtptest/server.py
lazr/smtptest/version.txt
lazr/smtptest/docs/README.rst
lazr/smtptest/docs/README_fixture.py
lazr/smtptest/docs/__init__.py
lazr/smtptest/docs/fixture.py
lazr/smtptest/docs/queue.rst
lazr/smtptest/docs/queue_fixture.py
lazr/smtptest/docs/usage.rst
lazr/smtptest/docs/usage_fixture.py
lazr/smtptest/tests/__init__.py